zlest/__init__.py
zlest/anhuisheng.py
zlest/anhuisheng1.py
zlest/enshizhou.py
zlest/ezhoushi.py
zlest/gcjs_anhui_hefei.py
zlest/gcjs_anhui_shenghui.py
zlest/gcjs_guangdong_guangzhou.py
zlest/gcjs_guangxi_guilin.py
zlest/gcjs_jiangsu_suzhou.py
zlest/gcjs_shandong_pingdu.py
zlest/gcjs_shandong_weihai.py
zlest/gcjs_shanghai_shanghai.py
zlest/gcjs_shanxi_shangluo.py
zlest/gcjs_xinjinag_weiwuer.py
zlest/gcjs_yunnan_yunnan.py
zlest/gcjs_zhejiang_jiaotong.py
zlest/gcjs_zhejiang_ningbo.py
zlest/gcjs_zhejiang_wenzhou.py
zlest/gcjs_zhejiang_zhejiang.py
zlest/ggzy_beijing_haidian.py
zlest/ggzy_gansu_linxia.py
zlest/ggzy_hebei_cangzhou.py
zlest/ggzy_henan_henan.py
zlest/ggzy_henan_henan1.py
zlest/ggzy_hubei_anlu.py
zlest/ggzy_hubei_chibi.py
zlest/ggzy_hubei_daye.py
zlest/ggzy_hubei_ezhou.py
zlest/ggzy_hubei_guangshui.py
zlest/ggzy_hubei_hanchuan.py
zlest/ggzy_hubei_honghu.py
zlest/ggzy_hubei_hubei.py
zlest/ggzy_hubei_hubei1.py
zlest/ggzy_hubei_hubei2.py
zlest/ggzy_hubei_jingzhou.py
zlest/ggzy_hubei_macheng.py
zlest/ggzy_hubei_wuxue.py
zlest/ggzy_hubei_xianning.py
zlest/ggzy_hubei_yicheng.py
zlest/ggzy_hubei_yingcheng.py
zlest/ggzy_hubei_zhijiang.py
zlest/ggzy_hubei_zhongxiang.py
zlest/ggzy_hunan_xiangxi.py
zlest/ggzy_jilin_jilin.py
zlest/ggzy_neimenggu_neimenggu.py
zlest/ggzy_shaoxing_shangyuqu.py
zlest/ggzy_tianjin_tianjin.py
zlest/ggzy_zhejiang_kaihuaxian.py
zlest/ggzy_zhejiang_wuxingqu.py
zlest/ggzy_zhejiang_xianjuxian.py
zlest/ggzy_zhejiang_zhejiang.py
zlest/guangdongsheng.py
zlest/guangxisheng.py
zlest/guizhousheng.py
zlest/henansheng.py
zlest/hubeisheng.py
zlest/hunansheng.py
zlest/jiangxisheng.py
zlest/neimenggu.py
zlest/qinghaisheng.py
zlest/qinghaisheng1.py
zlest/shaoyangxian.py
zlest/shenzhenshi.py
zlest/sichuansheng.py
zlest/task.py
zlest/wuxishi.py
zlest/zfcg_beijing_beijing.py
zlest/zfcg_beijing_mentougou.py
zlest/zfcg_hubei_wufengxian.py
zlest/zfcg_jilin_jilin.py
zlest/zfcg_liaoning_liaoning.py
zlest/zfcg_liaoning_shenghui.py
zlest/zfcg_ningbo_yinzhou.py
zlest-1.1.9.dist-info/METADATA
zlest-1.1.9.dist-info/WHEEL
zlest-1.1.9.dist-info/top_level.txt
zlest-1.1.9.dist-info/RECORD
